policyengine_canada/__init__.py
policyengine_canada/constants.py
policyengine_canada/entities.py
policyengine_canada/model_api.py
policyengine_canada/modelled_policies.yaml
policyengine_canada/typing.py
policyengine_canada/data/__init__.py
policyengine_canada/data/datasets/__init__.py
policyengine_canada/data/datasets/country_template_dataset.py
policyengine_canada/parameters/gov/cra/README.md
policyengine_canada/parameters/gov/cra/benefits/ccb/README.md
policyengine_canada/parameters/gov/cra/benefits/ccb/base.yaml
policyengine_canada/parameters/gov/cra/benefits/ccb/divisor.yaml
policyengine_canada/parameters/gov/cra/benefits/ccb/reduction/four_or_more_children.yaml
policyengine_canada/parameters/gov/cra/benefits/ccb/reduction/one_child.yaml
policyengine_canada/parameters/gov/cra/benefits/ccb/reduction/three_children.yaml
policyengine_canada/parameters/gov/cra/benefits/ccb/reduction/two_children.yaml
policyengine_canada/parameters/gov/cra/benefits/cdb/README.md
policyengine_canada/parameters/gov/cra/benefits/cdb/base.yaml
policyengine_canada/parameters/gov/cra/benefits/cdb/reduction/one_child.yaml
policyengine_canada/parameters/gov/cra/benefits/cdb/reduction/two_or_more_children.yaml
policyengine_canada/parameters/gov/cra/benefits/cwb/README.md
policyengine_canada/parameters/gov/cra/benefits/cwb/eligible_age.yaml
policyengine_canada/parameters/gov/cra/benefits/cwb/working_income_sources.yaml
policyengine_canada/parameters/gov/cra/benefits/cwb/amount/disability_supplement.yaml
policyengine_canada/parameters/gov/cra/benefits/cwb/amount/family.yaml
policyengine_canada/parameters/gov/cra/benefits/cwb/amount/single.yaml
policyengine_canada/parameters/gov/cra/benefits/cwb/phase_in/README.md
policyengine_canada/parameters/gov/cra/benefits/cwb/phase_in/disability_supplement.yaml
policyengine_canada/parameters/gov/cra/benefits/cwb/phase_in/base/family.yaml
policyengine_canada/parameters/gov/cra/benefits/cwb/phase_in/base/single.yaml
policyengine_canada-0.96.6.dist-info/licenses/LICENSE
policyengine_canada-0.96.6.dist-info/METADATA
policyengine_canada-0.96.6.dist-info/WHEEL
policyengine_canada-0.96.6.dist-info/top_level.txt
policyengine_canada-0.96.6.dist-info/RECORD
