Metadata-Version: 2.4
Name: policyengine-canada
Version: 0.96.6
Summary: Microsimulation model for Canada's tax-benefit system.
Home-page: https://github.com/policyengine/policyengine-canada
Author: PolicyEngine
Author-email: hello@policyengine.org
License: https://www.fsf.org/licensing/licenses/agpl-3.0.html
Keywords: tax benefit microsimulation framework
Classifier: Development Status :: 5 - Production/Stable
Classifier: License :: OSI Approved :: GNU Affero General Public License v3
Classifier: Operating System :: POSIX
Classifier: Programming Language :: Python
Classifier: Programming Language :: Python :: 3.10
Classifier: Programming Language :: Python :: 3.11
Classifier: Programming Language :: Python :: 3.12
Classifier: Programming Language :: Python :: 3.13
Classifier: Topic :: Scientific/Engineering :: Information Analysis
Requires-Python: >=3.10
License-File: LICENSE
Requires-Dist: policyengine_core>=3.23.6
Requires-Dist: black[jupyter]
Requires-Dist: coverage<7
Requires-Dist: dpath<3
Requires-Dist: h5py<4,>=3
Requires-Dist: linecheck<1
Requires-Dist: microdf_python>=1.2.1
Requires-Dist: nptyping<2
Requires-Dist: numexpr<3
Requires-Dist: pandas>=2.2.0
Requires-Dist: plotly<6,>=5.6.0
Requires-Dist: pytest
Requires-Dist: requests<3,>=2.27.1
Requires-Dist: sortedcontainers<3
Requires-Dist: tqdm<5,>=4.46.0
Requires-Dist: wheel<1
Requires-Dist: yaml-changelog==0.3.0
Provides-Extra: dev
Requires-Dist: furo; extra == "dev"
Requires-Dist: jupyter-book; extra == "dev"
Requires-Dist: markupsafe; extra == "dev"
Requires-Dist: pydata-sphinx-theme; extra == "dev"
Requires-Dist: sphinx; extra == "dev"
Requires-Dist: sphinx-argparse; extra == "dev"
Requires-Dist: sphinx-math-dollar; extra == "dev"
Dynamic: author
Dynamic: author-email
Dynamic: classifier
Dynamic: description
Dynamic: description-content-type
Dynamic: home-page
Dynamic: keywords
Dynamic: license
Dynamic: license-file
Dynamic: provides-extra
Dynamic: requires-dist
Dynamic: requires-python
Dynamic: summary
